f1z1_async_http/__init__.py
f1z1_async_http/components/__init__.py
f1z1_async_http/components/hook.py
f1z1_async_http/components/notifier.py
f1z1_async_http/components/options.py
f1z1_async_http/src/__init__.py
f1z1_async_http/src/_type.py
f1z1_async_http/src/builder.py
f1z1_async_http/src/client.py
f1z1_async_http/src/defaults.py
f1z1_async_http/src/manager.py
f1z1_async_http-0.3.1.dist-info/LICENSE
f1z1_async_http-0.3.1.dist-info/METADATA
f1z1_async_http-0.3.1.dist-info/WHEEL
f1z1_async_http-0.3.1.dist-info/top_level.txt
f1z1_async_http-0.3.1.dist-info/RECORD
